sdh-qualitative-metrics
setup.cfg
setup.py
SDH_Qualitative_Metrics.egg-info/PKG-INFO
SDH_Qualitative_Metrics.egg-info/SOURCES.txt
SDH_Qualitative_Metrics.egg-info/dependency_links.txt
SDH_Qualitative_Metrics.egg-info/namespace_packages.txt
SDH_Qualitative_Metrics.egg-info/requires.txt
SDH_Qualitative_Metrics.egg-info/top_level.txt
sdh/__init__.py
sdh/metrics/__init__.py
sdh/metrics/qualitative/__init__.py
sdh/metrics/qualitative/api.py
sdh/metrics/qualitative/config.py
sdh/metrics/qualitative/store.py