Metadata-Version: 1.1
Name: SDH-Qualitative-Metrics
Version: 0.0.6
Summary: A service that calculates a bunch of qualitative metrics on data from SCM and CI domains.
Home-page: https://github.com/smartdeveloperhub/sdh-qualitative-metrics
Author: Fernando Serena
Author-email: fernando.serena@centeropenmiddleware.com
License: Apache 2
Download-URL: https://github.com/smartdeveloperhub/sdh-qualitative-metrics/tarball/0.0.1
Keywords: linked-data,ontology,path,sdh,metrics
Platform: UNKNOWN
